xo/__init__.py
xo/redis.py
xo/xo.py
xo.redis-0.2.6.1.dist-info/METADATA
xo.redis-0.2.6.1.dist-info/WHEEL
xo.redis-0.2.6.1.dist-info/entry_points.txt
xo.redis-0.2.6.1.dist-info/top_level.txt
xo.redis-0.2.6.1.dist-info/RECORD
