Metadata-Version: 2.1
Name: xo.redis
Version: 0.2.6.1
Summary: Use redis db as an object. expando like a dictionary or an object
Home-page: https://github.com/fire17/expando
Author: Tami
Author-email: fire17@gmail.com
License: UNKNOWN
Platform: UNKNOWN
Classifier: Programming Language :: Python :: 3
Classifier: License :: OSI Approved :: MIT License
Classifier: Operating System :: OS Independent
Requires-Dist: dill
Requires-Dist: expando
Requires-Dist: redis
